odoo10_addon_sale_stock_picking_note-10.0.1.1.0-nspkg.pth
odoo/addons/sale_stock_picking_note/README.rst
odoo/addons/sale_stock_picking_note/__init__.py
odoo/addons/sale_stock_picking_note/__manifest__.py
odoo/addons/sale_stock_picking_note/i18n/es.po
odoo/addons/sale_stock_picking_note/i18n/sale_stock_picking_note.pot
odoo/addons/sale_stock_picking_note/models/__init__.py
odoo/addons/sale_stock_picking_note/models/sale_stock.py
odoo/addons/sale_stock_picking_note/readme/CONTRIBUTORS.rst
odoo/addons/sale_stock_picking_note/readme/DESCRIPTION.rst
odoo/addons/sale_stock_picking_note/readme/USAGE.rst
odoo/addons/sale_stock_picking_note/static/description/icon.png
odoo/addons/sale_stock_picking_note/static/description/index.html
odoo/addons/sale_stock_picking_note/tests/__init__.py
odoo/addons/sale_stock_picking_note/tests/test_sale_stock_picking_note.py
odoo/addons/sale_stock_picking_note/views/sale_order_view.xml
odoo10_addon_sale_stock_picking_note-10.0.1.1.0.dist-info/METADATA
odoo10_addon_sale_stock_picking_note-10.0.1.1.0.dist-info/WHEEL
odoo10_addon_sale_stock_picking_note-10.0.1.1.0.dist-info/namespace_packages.txt
odoo10_addon_sale_stock_picking_note-10.0.1.1.0.dist-info/top_level.txt
odoo10_addon_sale_stock_picking_note-10.0.1.1.0.dist-info/RECORD
