Metadata-Version: 2.1
Name: odoo10-addon-sale-stock-picking-note
Version: 10.0.1.1.0
Summary: Add picking note in sale and purchase order
Home-page: https://github.com/OCA/sale-workflow
Author: Tecnativa, Odoo Community Association (OCA)
Author-email: support@odoo-community.org
License: AGPL-3
Platform: UNKNOWN
Classifier: Programming Language :: Python
Classifier: Framework :: Odoo
Classifier: License :: OSI Approved :: GNU Affero General Public License v3
Requires-Python: ~=2.7
Requires-Dist: odoo (<10.1dev,>=10.0)
